flash_flask/__init__.py
flash_flask/core/App.py
flash_flask/core/Sessions.py
flash_flask/core/Utils.py
flash_flask/core/__init__.py
flash_flask/core/template.py
flash_flask/core/routes/Mapper.py
flash_flask/core/routes/__init__.py
flash_flask/core/routes/decorator.py
flash_flask/db/__init__.py
flash_flask/db/mysql.py
flash_flask/db/sqlite.py
flash_flask_python-1.0.6.dist-info/METADATA
flash_flask_python-1.0.6.dist-info/WHEEL
flash_flask_python-1.0.6.dist-info/top_level.txt
flash_flask_python-1.0.6.dist-info/RECORD
