Metadata-Version: 2.1
Name: flash_flask_python
Version: 1.0.6
Summary: Make Flask Better
Author: Alex ZALO
Requires-Dist: Flask==3.0.0
Provides-Extra: mysql
Requires-Dist: mysql-connector-python==8.2.0; extra == "mysql"
